cobaltpy/__init__.py
cobaltpy-0.1.0.dist-info/LICENSE
cobaltpy-0.1.0.dist-info/METADATA
cobaltpy-0.1.0.dist-info/WHEEL
cobaltpy-0.1.0.dist-info/RECORD
