Metadata-Version: 2.1
Name: cobaltpy
Version: 0.1.0
Summary: Download files using Cobalt.
License: Apache
Author: Smugaski
Requires-Python: >=3.11,<4.0
Classifier: License :: Other/Proprietary License
Classifier: Programming Language :: Python :: 3
Classifier: Programming Language :: Python :: 3.11
Classifier: Programming Language :: Python :: 3.12
Requires-Dist: aiohttp (>=3.10.4,<4.0.0)
